pytreez/__init__.py
pytreez/v1.py
pytreez/v2.py
pytreez-1.4.0.dist-info/WHEEL
pytreez-1.4.0.dist-info/METADATA
pytreez-1.4.0.dist-info/RECORD
